{
    "Tasks": {
        "running": 1,
        "sleeping": 32,
        "stopped": 0,
        "total": 33,
        "zombie": 0
    },
    "cpu": {
        "hi": 0.0,
        "id": 100.0,
        "ni": 0.0,
        "si": 0.0,
        "st": 0.0,
        "sy": 0.0,
        "us": 0.0,
        "wa": 0.0
    },
    "load_average": [
        0.10000000149011612,
        0.10000000149011612,
        0.03999999910593033
    ],
    "memory": {
        "buff/cache": 1258.0999755859375,
        "free": 10489.900390625,
        "total": 12528.900390625,
        "used": 780.9000244140625
    },
    "swap": {
        "avail Mem": 11488.5,
        "free": 4096.0,
        "total": 4096.0,
        "used": 0.0
    },
    "system_time": "21:32:54",
    "uptime": "8:14",
    "users": 0
}
